prlps_ya300/__init__.py
prlps_ya300/__main__.py
prlps_ya300/api.py
prlps_ya300/log.py
prlps_ya300/utils.py
prlps_ya300-0.0.1.dist-info/LICENSE.txt
prlps_ya300-0.0.1.dist-info/METADATA
prlps_ya300-0.0.1.dist-info/WHEEL
prlps_ya300-0.0.1.dist-info/top_level.txt
prlps_ya300-0.0.1.dist-info/RECORD
