Metadata-Version: 2.1
Name: prlps_ya300
Version: 0.0.1
Summary: получения содержания статей или видео с YouTube и запуска API-сервера для суммаризации через сервис 300.ya.ru
Home-page: https://github.com/gniloyprolaps/ya300
Author: prolapser
License: LICENSE.txt
Classifier: Development Status :: 4 - Beta
Classifier: Intended Audience :: Developers
Classifier: License :: OSI Approved :: MIT License
Classifier: Operating System :: OS Independent
Requires-Python: >=3.10
License-File: LICENSE.txt
Requires-Dist: fastapi
Requires-Dist: pydantic
Requires-Dist: uvicorn
Requires-Dist: httpx
